git_source_track/__init__.py
git_source_track/cmd.py
git_source_track/compat.py
git_source_track/git_log.py
git_source_track/version.py
git_source_track-0.4.1.dist-info/LICENSE
git_source_track-0.4.1.dist-info/METADATA
git_source_track-0.4.1.dist-info/WHEEL
git_source_track-0.4.1.dist-info/entry_points.txt
git_source_track-0.4.1.dist-info/top_level.txt
git_source_track-0.4.1.dist-info/RECORD
