Metadata-Version: 2.1
Name: git-source-track
Version: 0.4.1
Summary: Track changes between two git repositories
Home-page: https://github.com/virtuald/git-source-track
Author: Dustin Spicuzza
Author-email: dustin@virtualroadside.com
License: Apache 2.0
Classifier: Development Status :: 5 - Production/Stable
Classifier: Operating System :: OS Independent
Classifier: Environment :: Console
Classifier: Intended Audience :: Developers
Classifier: Programming Language :: Python
Classifier: Programming Language :: Python :: 2.7
Classifier: Programming Language :: Python :: 3
Classifier: License :: OSI Approved :: Apache Software License
License-File: LICENSE
Requires-Dist: sh
Requires-Dist: six
